pandocker_lua_filters/__init__.py
pandocker_lua_filters/version.py
pandocker_lua_filters-0.0.33.data/data/bin/pandocker/svgbob
pandocker_lua_filters-0.0.33.data/data/bin/pandocker/svgbob.bin
pandocker_lua_filters-0.0.33.data/data/bin/pandocker/svgbob.exe
pandocker_lua_filters-0.0.33.data/data/share/lua/5.3/pandocker/aafigure.lua
pandocker_lua_filters-0.0.33.data/data/share/lua/5.3/pandocker/csv2table-simple.lua
pandocker_lua_filters-0.0.33.data/data/share/lua/5.3/pandocker/csv2table.lua
pandocker_lua_filters-0.0.33.data/data/share/lua/5.3/pandocker/default_loader.lua
pandocker_lua_filters-0.0.33.data/data/share/lua/5.3/pandocker/docx-appendixheadings.lua
pandocker_lua_filters-0.0.33.data/data/share/lua/5.3/pandocker/docx-apply-cell-styles.lua
pandocker_lua_filters-0.0.33.data/data/share/lua/5.3/pandocker/docx-colored-span.lua
pandocker_lua_filters-0.0.33.data/data/share/lua/5.3/pandocker/docx-comment.lua
pandocker_lua_filters-0.0.33.data/data/share/lua/5.3/pandocker/docx-custom-span-styles.lua
pandocker_lua_filters-0.0.33.data/data/share/lua/5.3/pandocker/docx-extract-bullet-lists.lua
pandocker_lua_filters-0.0.33.data/data/share/lua/5.3/pandocker/docx-image-styles.lua
pandocker_lua_filters-0.0.33.data/data/share/lua/5.3/pandocker/docx-pagebreak-toc.lua
pandocker_lua_filters-0.0.33.data/data/share/lua/5.3/pandocker/docx-unnumberedheadings.lua
pandocker_lua_filters-0.0.33.data/data/share/lua/5.3/pandocker/hide-frontpage-metadata.lua
pandocker_lua_filters-0.0.33.data/data/share/lua/5.3/pandocker/listingtable.lua
pandocker_lua_filters-0.0.33.data/data/share/lua/5.3/pandocker/metadata-file.yaml
pandocker_lua_filters-0.0.33.data/data/share/lua/5.3/pandocker/preprocess.lua
pandocker_lua_filters-0.0.33.data/data/share/lua/5.3/pandocker/removable-note.lua
pandocker_lua_filters-0.0.33.data/data/share/lua/5.3/pandocker/svgbob.lua
pandocker_lua_filters-0.0.33.data/data/share/lua/5.3/pandocker/svgconvert.lua
pandocker_lua_filters-0.0.33.dist-info/LICENSE
pandocker_lua_filters-0.0.33.dist-info/METADATA
pandocker_lua_filters-0.0.33.dist-info/WHEEL
pandocker_lua_filters-0.0.33.dist-info/entry_points.txt
pandocker_lua_filters-0.0.33.dist-info/top_level.txt
pandocker_lua_filters-0.0.33.dist-info/RECORD
