Metadata-Version: 2.1
Name: pandocker-lua-filters
Version: 0.0.33
Summary: Lua filter collection for pandoc
Home-page: https://github.com/pandocker/pandocker-lua-filters
Author: pandocker
Author-email: pandocker@github.com
Project-URL: Bug Reports, https://github.com/pandocker/pandocker-lua-filters/issues
Project-URL: Source, https://github.com/pandocker/pandocker-lua-filters/
Keywords: Pandoc Lua Filter
Classifier: Development Status :: 3 - Alpha
Classifier: Intended Audience :: Developers
Classifier: Topic :: Software Development :: Build Tools
Classifier: License :: OSI Approved :: MIT License
Classifier: Programming Language :: Python :: 3.5
Classifier: Programming Language :: Python :: 3.6
Classifier: Programming Language :: Python :: 3.7
License-File: LICENSE
Requires-Dist: aafigure
